news_please-1.6.15.dist-info/licenses/LICENSE.txt
newsplease/NewsArticle.py
newsplease/__init__.py
newsplease/__main__.py
newsplease/config.py
newsplease/helper.py
newsplease/single_crawler.py
newsplease/config/config.cfg
newsplease/config/config_lib.cfg
newsplease/config/sitelist.hjson
newsplease/crawler/__init__.py
newsplease/crawler/commoncrawl_crawler.py
newsplease/crawler/commoncrawl_extractor.py
newsplease/crawler/items.py
newsplease/crawler/response_decoder.py
newsplease/crawler/simple_crawler.py
newsplease/crawler/spiders/__init__.py
newsplease/crawler/spiders/download_crawler.py
newsplease/crawler/spiders/gdelt_crawler.py
newsplease/crawler/spiders/newsplease_spider.py
newsplease/crawler/spiders/recursive_crawler.py
newsplease/crawler/spiders/recursive_sitemap_crawler.py
newsplease/crawler/spiders/rss_crawler.py
newsplease/crawler/spiders/sitemap_crawler.py
newsplease/examples/__init__.py
newsplease/examples/commoncrawl.py
newsplease/examples/downloadfromfile.py
newsplease/examples/downloadfromurl.py
newsplease/helper_classes/__init__.py
newsplease/helper_classes/class_loader.py
newsplease/helper_classes/heuristics.py
newsplease/helper_classes/parse_crawler.py
newsplease/helper_classes/savepath_parser.py
newsplease/helper_classes/url_extractor.py
newsplease/helper_classes/sub_classes/__init__.py
newsplease/helper_classes/sub_classes/heuristics_manager.py
newsplease/pipeline/__init__.py
newsplease/pipeline/pipelines.py
newsplease/pipeline/extractor/__init__.py
newsplease/pipeline/extractor/article_candidate.py
newsplease/pipeline/extractor/article_extractor.py
newsplease/pipeline/extractor/cleaner.py
newsplease/pipeline/extractor/comparer/__init__.py
newsplease/pipeline/extractor/comparer/comparer.py
newsplease/pipeline/extractor/comparer/comparer_Language.py
newsplease/pipeline/extractor/comparer/comparer_author.py
newsplease/pipeline/extractor/comparer/comparer_date.py
newsplease/pipeline/extractor/comparer/comparer_description.py
newsplease/pipeline/extractor/comparer/comparer_text.py
news_please-1.6.15.dist-info/METADATA
news_please-1.6.15.dist-info/WHEEL
news_please-1.6.15.dist-info/entry_points.txt
news_please-1.6.15.dist-info/top_level.txt
news_please-1.6.15.dist-info/RECORD
