Metadata-Version: 2.4
Name: news-please
Version: 1.6.15
Summary: news-please is an open source easy-to-use news extractor that just works.
Home-page: https://github.com/fhamborg/news-please
Download-URL: https://github.com/fhamborg/news-please
Author: Felix Hamborg
Author-email: felix.hamborg@uni-konstanz.de
License: Apache License 2.0
Keywords: news crawler news scraper news extractor crawler extractor scraper information retrieval
Classifier: Development Status :: 5 - Production/Stable
Classifier: Environment :: Console
Classifier: Intended Audience :: Developers
Classifier: Intended Audience :: Science/Research
Classifier: License :: OSI Approved :: Apache Software License
Classifier: Operating System :: MacOS
Classifier: Operating System :: Microsoft
Classifier: Operating System :: POSIX :: Linux
Classifier: Programming Language :: Python :: 3.8
Classifier: Programming Language :: Python :: 3.9
Classifier: Programming Language :: Python :: 3.10
Classifier: Programming Language :: Python :: 3.11
Classifier: Programming Language :: Python :: 3.12
Classifier: Topic :: Internet
Classifier: Topic :: Scientific/Engineering :: Information Analysis
License-File: LICENSE.txt
Requires-Dist: Scrapy>=1.1.0
Requires-Dist: PyMySQL>=0.7.9
Requires-Dist: psycopg2-binary>=2.8.4
Requires-Dist: hjson>=1.5.8
Requires-Dist: elasticsearch>=2.4
Requires-Dist: beautifulsoup4>=4.3.2
Requires-Dist: readability-lxml>=0.6.2
Requires-Dist: langdetect>=1.0.7
Requires-Dist: python-dateutil>=2.4.0
Requires-Dist: plac>=0.9.6
Requires-Dist: dotmap>=1.2.17
Requires-Dist: PyDispatcher>=2.0.5
Requires-Dist: warcio>=1.3.3
Requires-Dist: ago>=0.0.9
Requires-Dist: six>=1.10.0
Requires-Dist: lxml>=3.3.5
Requires-Dist: hurry.filesize>=0.9
Requires-Dist: bs4
Requires-Dist: faust-cchardet>=2.1.18
Requires-Dist: boto3
Requires-Dist: redis
Requires-Dist: newspaper4k>=0.9.3.1
Requires-Dist: lxml-html-clean>=0.1.1
Requires-Dist: typing-extensions>=4.7.0
Requires-Dist: pywin32>=220; sys_platform == "win32"
Dynamic: author
Dynamic: author-email
Dynamic: classifier
Dynamic: description
Dynamic: download-url
Dynamic: home-page
Dynamic: keywords
Dynamic: license
Dynamic: license-file
Dynamic: provides-extra
Dynamic: requires-dist
Dynamic: summary
